<?xml version="1.0" encoding="UTF-8" standalone="no"?>
<!-- Generated 2017-8-16 9:53:24 by Hibernate Tools 5.2.3.Final --><!DOCTYPE hibernate-mapping PUBLIC "-//Hibernate/Hibernate Mapping DTD 3.0//EN" "http://www.hibernate.org/dtd/hibernate-mapping-3.0.dtd">
<hibernate-mapping auto-import="true" default-access="property" default-cascade="none" default-lazy="true">
    <class dynamic-insert="false" dynamic-update="false" mutable="true" name="org.hyatt.model.Stats" optimistic-lock="version" polymorphism="implicit" select-before-update="false" table="Stats">
        <id name="id" type="long">
            <column name="id"/>
            <generator class="assigned"/>
        </id>
        <property generated="never" lazy="false" name="clusterDict" optimistic-lock="true" type="string" unique="false">
            <column name="cluster_dict"/>
        </property>
        <property generated="never" lazy="false" name="gmDict" optimistic-lock="true" type="string" unique="false">
            <column name="gm_dict"/>
        </property>
        <property generated="never" lazy="false" name="lastTime" optimistic-lock="true" type="timestamp" unique="false">
            <column length="19" name="last_time"/>
        </property>
        <property generated="never" lazy="false" name="startTime" optimistic-lock="true" type="timestamp" unique="false">
            <column length="19" name="start_time"/>
        </property>
        <property generated="never" lazy="false" name="totalcount" optimistic-lock="true" type="long" unique="false">
            <column name="totalcount" not-null="true"/>
        </property>
        <property generated="never" lazy="false" name="updatetime" optimistic-lock="true" type="timestamp" unique="false">
            <column length="19" name="updatetime"/>
        </property>
    </class>
</hibernate-mapping>
